LICENSE
MANIFEST.in
README.md
setup.py
rcmd/__init__.py
rcmd.egg-info/PKG-INFO
rcmd.egg-info/SOURCES.txt
rcmd.egg-info/dependency_links.txt
rcmd.egg-info/not-zip-safe
rcmd.egg-info/top_level.txt