Metadata-Version: 1.1
Name: rcmd
Version: 1.0.1
Summary: Like Python's cmd module, but uses regex based handlers instead!
Home-page: https://github.com/plausibility/rcmd.py
Author: plausibility
Author-email: chris@gibsonsec.org
License: MIT
Keywords: cmd command line loop
Platform: UNKNOWN
Classifier: Development Status :: 4 - Beta
Classifier: Intended Audience :: Developers
Classifier: License :: OSI Approved :: MIT License
Classifier: Operating System :: OS Independent
Classifier: Programming Language :: Python :: 2
Classifier: Programming Language :: Python :: 3
